[
  {
    "type": "chat",
    "user": "touh678",
    "content": "Oubliez pas les amis, 🩷 du jour + ajoutez tout le panel si on veut monter",
    "datetime": "2026-04-21 20:37:23"
  },
  {
    "type": "chat",
    "user": "touh678",
    "content": "Oubliez pas les amis, 🩷 du jour + ajoutez tout le panel si on veut monter",
    "datetime": "2026-04-21 20:37:23"
  },
  {
    "type": "chat",
    "user": "orlea66",
    "content": "@dadi enchanté",
    "datetime": "2026-04-21 20:37:23"
  },
  {
    "type": "chat",
    "user": "mr.propre51_",
    "content": "",
    "datetime": "2026-04-21 20:37:23"
  },
  {
    "type": "chat",
    "user": "mehdiamrouche18",
    "content": "@Orléa enchanté",
    "datetime": "2026-04-21 20:37:23"
  },
  {
    "type": "chat",
    "user": "orlea66",
    "content": "",
    "datetime": "2026-04-21 20:37:23"
  },
  {
    "type": "like",
    "user": "mr.propre51_",
    "content": "?",
    "datetime": "2026-04-21 20:37:23"
  },
  {
    "type": "chat",
    "user": "mama.love264",
    "content": "a rejoint le live",
    "datetime": "2026-04-21 20:37:23"
  },
  {
    "type": "chat",
    "user": "touh678",
    "content": "Oubliez pas les amis, 🩷 du jour + ajoutez tout le panel si on veut monter",
    "datetime": "2026-04-21 20:37:23"
  },
  {
    "type": "chat",
    "user": "touh678",
    "content": "Oubliez pas les amis, 🩷 du jour + ajoutez tout le panel si on veut monter",
    "datetime": "2026-04-21 20:37:23"
  },
  {
    "type": "chat",
    "user": "orlea66",
    "content": "@dadi enchanté",
    "datetime": "2026-04-21 20:37:23"
  },
  {
    "type": "chat",
    "user": "mr.propre51_",
    "content": "",
    "datetime": "2026-04-21 20:37:23"
  },
  {
    "type": "chat",
    "user": "mehdiamrouche18",
    "content": "@Orléa enchanté",
    "datetime": "2026-04-21 20:37:23"
  },
  {
    "type": "chat",
    "user": "orlea66",
    "content": "",
    "datetime": "2026-04-21 20:37:23"
  },
  {
    "type": "chat",
    "user": "mama.love264",
    "content": "a rejoint le live",
    "datetime": "2026-04-21 20:37:23"
  },
  {
    "type": "cadeau",
    "user": "orlea66 → viraltiktok8389",
    "content": "Thumbs Up",
    "datetime": "2026-04-21 20:37:24"
  },
  {
    "type": "like",
    "user": "mr.propre51_",
    "content": "?",
    "datetime": "2026-04-21 20:37:24"
  },
  {
    "type": "cadeau",
    "user": "orlea66 → viraltiktok8389",
    "content": "Thumbs Up",
    "datetime": "2026-04-21 20:37:27"
  },
  {
    "type": "chat",
    "user": "equitation640",
    "content": "a rejoint le live",
    "datetime": "2026-04-21 20:37:28"
  },
  {
    "type": "chat",
    "user": "toimoi653",
    "content": "a rejoint le live",
    "datetime": "2026-04-21 20:37:30"
  },
  {
    "type": "cadeau",
    "user": "mo78888888888 → raphaelboost",
    "content": "Heart Me",
    "datetime": "2026-04-21 20:37:32"
  },
  {
    "type": "chat",
    "user": "c.ch7150",
    "content": "a rejoint le live",
    "datetime": "2026-04-21 20:37:33"
  },
  {
    "type": "like",
    "user": "mr.propre51_",
    "content": "?",
    "datetime": "2026-04-21 20:37:34"
  },
  {
    "type": "chat",
    "user": "alexz.jaya.motor",
    "content": "a rejoint le live",
    "datetime": "2026-04-21 20:37:34"
  },
  {
    "type": "chat",
    "user": "h153593",
    "content": "a rejoint le live",
    "datetime": "2026-04-21 20:37:35"
  },
  {
    "type": "chat",
    "user": "abdul_muhtolib01",
    "content": "a rejoint le live",
    "datetime": "2026-04-21 20:37:37"
  },
  {
    "type": "chat",
    "user": "mariasouza1936",
    "content": "a rejoint le live",
    "datetime": "2026-04-21 20:37:38"
  },
  {
    "type": "chat",
    "user": "dy2w9afbhtjg",
    "content": "a rejoint le live",
    "datetime": "2026-04-21 20:37:39"
  },
  {
    "type": "like",
    "user": "mr.propre51_",
    "content": "?",
    "datetime": "2026-04-21 20:37:39"
  },
  {
    "type": "chat",
    "user": "idaroyani270",
    "content": "a rejoint le live",
    "datetime": "2026-04-21 20:37:39"
  },
  {
    "type": "chat",
    "user": "nukartaaolsen",
    "content": "a rejoint le live",
    "datetime": "2026-04-21 20:37:40"
  },
  {
    "type": "like",
    "user": "mr.propre51_",
    "content": "?",
    "datetime": "2026-04-21 20:37:41"
  },
  {
    "type": "like",
    "user": "mama.love264",
    "content": "?",
    "datetime": "2026-04-21 20:37:42"
  },
  {
    "type": "cadeau",
    "user": "mikamooz66 → mehdiamrouche18",
    "content": "Love you so much",
    "datetime": "2026-04-21 20:37:42"
  },
  {
    "type": "chat",
    "user": "zeynb.ibrahimova8",
    "content": "a rejoint le live",
    "datetime": "2026-04-21 20:37:44"
  },
  {
    "type": "like",
    "user": "x_ayoub__34_x",
    "content": "?",
    "datetime": "2026-04-21 20:37:44"
  },
  {
    "type": "cadeau",
    "user": "mikamooz66 → mehdiamrouche18",
    "content": "Love you so much",
    "datetime": "2026-04-21 20:37:46"
  },
  {
    "type": "chat",
    "user": "sasuke44519",
    "content": "a rejoint le live",
    "datetime": "2026-04-21 20:37:47"
  },
  {
    "type": "like",
    "user": "x_ayoub__34_x",
    "content": "?",
    "datetime": "2026-04-21 20:37:48"
  },
  {
    "type": "like",
    "user": "zeynb.ibrahimova8",
    "content": "?",
    "datetime": "2026-04-21 20:37:49"
  },
  {
    "type": "chat",
    "user": "user369980535206",
    "content": "a rejoint le live",
    "datetime": "2026-04-21 20:37:50"
  },
  {
    "type": "chat",
    "user": "mo78888888888",
    "content": "‏سلم",
    "datetime": "2026-04-21 20:37:50"
  },
  {
    "type": "cadeau",
    "user": "mehdiamrouche18 → le.r7380",
    "content": "Rose",
    "datetime": "2026-04-21 20:37:50"
  },
  {
    "type": "like",
    "user": "fayssal.fayssal991",
    "content": "?",
    "datetime": "2026-04-21 20:37:51"
  },
  {
    "type": "cadeau",
    "user": "mehdiamrouche18 → touh678",
    "content": "Rose",
    "datetime": "2026-04-21 20:37:52"
  },
  {
    "type": "cadeau",
    "user": "mehdiamrouche18 → le.r7380",
    "content": "Rose",
    "datetime": "2026-04-21 20:37:53"
  },
  {
    "type": "cadeau",
    "user": "mehdiamrouche18 → mikamooz66",
    "content": "Rose",
    "datetime": "2026-04-21 20:37:54"
  },
  {
    "type": "chat",
    "user": "rmnnnn00",
    "content": "a rejoint le live",
    "datetime": "2026-04-21 20:37:54"
  },
  {
    "type": "cadeau",
    "user": "mehdiamrouche18 → touh678",
    "content": "Rose",
    "datetime": "2026-04-21 20:37:55"
  },
  {
    "type": "like",
    "user": "x_ayoub__34_x",
    "content": "?",
    "datetime": "2026-04-21 20:37:55"
  },
  {
    "type": "cadeau",
    "user": "mehdiamrouche18 → orlea66",
    "content": "Rose",
    "datetime": "2026-04-21 20:37:56"
  },
  {
    "type": "cadeau",
    "user": "mehdiamrouche18 → mikamooz66",
    "content": "Rose",
    "datetime": "2026-04-21 20:37:58"
  },
  {
    "type": "like",
    "user": "mr.propre51_",
    "content": "?",
    "datetime": "2026-04-21 20:37:58"
  },
  {
    "type": "cadeau",
    "user": "mehdiamrouche18 → mr.propre51_",
    "content": "Rose",
    "datetime": "2026-04-21 20:37:59"
  },
  {
    "type": "chat",
    "user": "mohtaram517",
    "content": "a rejoint le live",
    "datetime": "2026-04-21 20:37:59"
  },
  {
    "type": "like",
    "user": "x_ayoub__34_x",
    "content": "?",
    "datetime": "2026-04-21 20:37:59"
  },
  {
    "type": "chat",
    "user": "alisondu85",
    "content": "a rejoint le live",
    "datetime": "2026-04-21 20:37:59"
  },
  {
    "type": "cadeau",
    "user": "mehdiamrouche18 → orlea66",
    "content": "Rose",
    "datetime": "2026-04-21 20:37:59"
  },
  {
    "type": "cadeau",
    "user": "mehdiamrouche18 → viraltiktok8389",
    "content": "Rose",
    "datetime": "2026-04-21 20:38:00"
  },
  {
    "type": "like",
    "user": "robarashid6",
    "content": "?",
    "datetime": "2026-04-21 20:38:00"
  },
  {
    "type": "cadeau",
    "user": "mehdiamrouche18 → mr.propre51_",
    "content": "Rose",
    "datetime": "2026-04-21 20:38:01"
  },
  {
    "type": "cadeau",
    "user": "mehdiamrouche18 → x_ayoub__34_x",
    "content": "Rose",
    "datetime": "2026-04-21 20:38:02"
  },
  {
    "type": "like",
    "user": "mr.propre51_",
    "content": "?",
    "datetime": "2026-04-21 20:38:02"
  },
  {
    "type": "like",
    "user": "robarashid6",
    "content": "?",
    "datetime": "2026-04-21 20:38:03"
  },
  {
    "type": "cadeau",
    "user": "mehdiamrouche18 → viraltiktok8389",
    "content": "Rose",
    "datetime": "2026-04-21 20:38:03"
  },
  {
    "type": "chat",
    "user": "ivanoliaghetseu0",
    "content": "a rejoint le live",
    "datetime": "2026-04-21 20:38:04"
  },
  {
    "type": "like",
    "user": "mr.propre51_",
    "content": "?",
    "datetime": "2026-04-21 20:38:04"
  },
  {
    "type": "like",
    "user": "robarashid6",
    "content": "?",
    "datetime": "2026-04-21 20:38:04"
  },
  {
    "type": "chat",
    "user": "www.tiktok.inad",
    "content": "a rejoint le live",
    "datetime": "2026-04-21 20:38:04"
  },
  {
    "type": "cadeau",
    "user": "mehdiamrouche18 → raphaelboost",
    "content": "Rose",
    "datetime": "2026-04-21 20:38:04"
  },
  {
    "type": "cadeau",
    "user": "mehdiamrouche18 → x_ayoub__34_x",
    "content": "Rose",
    "datetime": "2026-04-21 20:38:05"
  },
  {
    "type": "like",
    "user": "mama.love264",
    "content": "?",
    "datetime": "2026-04-21 20:38:05"
  },
  {
    "type": "chat",
    "user": "daniel44831",
    "content": "a rejoint le live",
    "datetime": "2026-04-21 20:38:06"
  },
  {
    "type": "cadeau",
    "user": "mehdiamrouche18 → raphaelboost",
    "content": "Rose",
    "datetime": "2026-04-21 20:38:08"
  },
  {
    "type": "like",
    "user": "mr.propre51_",
    "content": "?",
    "datetime": "2026-04-21 20:38:09"
  },
  {
    "type": "like",
    "user": "mama.love264",
    "content": "?",
    "datetime": "2026-04-21 20:38:09"
  },
  {
    "type": "chat",
    "user": "ronaldo26vlonjati",
    "content": "a rejoint le live",
    "datetime": "2026-04-21 20:38:10"
  },
  {
    "type": "chat",
    "user": "212122username",
    "content": "a rejoint le live",
    "datetime": "2026-04-21 20:38:10"
  },
  {
    "type": "like",
    "user": "mama.love264",
    "content": "?",
    "datetime": "2026-04-21 20:38:10"
  },
  {
    "type": "chat",
    "user": "robarashid6",
    "content": "@dadi",
    "datetime": "2026-04-21 20:38:10"
  },
  {
    "type": "chat",
    "user": "robarashid6",
    "content": "@dadi",
    "datetime": "2026-04-21 20:38:15"
  },
  {
    "type": "chat",
    "user": "orlea66",
    "content": "Super",
    "datetime": "2026-04-21 20:38:16"
  },
  {
    "type": "like",
    "user": "mama.love264",
    "content": "?",
    "datetime": "2026-04-21 20:38:16"
  },
  {
    "type": "like",
    "user": "robarashid6",
    "content": "?",
    "datetime": "2026-04-21 20:38:20"
  },
  {
    "type": "chat",
    "user": "peri.pasaribu35",
    "content": "a rejoint le live",
    "datetime": "2026-04-21 20:38:20"
  },
  {
    "type": "like",
    "user": "mama.love264",
    "content": "?",
    "datetime": "2026-04-21 20:38:22"
  },
  {
    "type": "like",
    "user": "mikamooz66",
    "content": "?",
    "datetime": "2026-04-21 20:38:24"
  },
  {
    "type": "like",
    "user": "robarashid6",
    "content": "?",
    "datetime": "2026-04-21 20:38:24"
  },
  {
    "type": "like",
    "user": "mikamooz66",
    "content": "?",
    "datetime": "2026-04-21 20:38:26"
  },
  {
    "type": "cadeau",
    "user": "mr.propre51_ → mehdiamrouche18",
    "content": "Freestyle",
    "datetime": "2026-04-21 20:38:29"
  },
  {
    "type": "like",
    "user": "mikamooz66",
    "content": "?",
    "datetime": "2026-04-21 20:38:29"
  },
  {
    "type": "chat",
    "user": "canavar_761",
    "content": "a rejoint le live",
    "datetime": "2026-04-21 20:38:29"
  },
  {
    "type": "like",
    "user": "robarashid6",
    "content": "?",
    "datetime": "2026-04-21 20:38:29"
  },
  {
    "type": "cadeau",
    "user": "catalanespano → raphaelboost",
    "content": "Heart Me",
    "datetime": "2026-04-21 20:38:31"
  },
  {
    "type": "like",
    "user": "mikamooz66",
    "content": "?",
    "datetime": "2026-04-21 20:38:31"
  },
  {
    "type": "cadeau",
    "user": "mr.propre51_ → mehdiamrouche18",
    "content": "Freestyle",
    "datetime": "2026-04-21 20:38:32"
  },
  {
    "type": "like",
    "user": "mr.propre51_",
    "content": "?",
    "datetime": "2026-04-21 20:38:33"
  },
  {
    "type": "chat",
    "user": "elliagill",
    "content": "a rejoint le live",
    "datetime": "2026-04-21 20:38:34"
  },
  {
    "type": "like",
    "user": "mr.propre51_",
    "content": "?",
    "datetime": "2026-04-21 20:38:36"
  },
  {
    "type": "chat",
    "user": "marianne59l",
    "content": "a rejoint le live",
    "datetime": "2026-04-21 20:38:37"
  },
  {
    "type": "chat",
    "user": "w.wahyu25",
    "content": "a rejoint le live",
    "datetime": "2026-04-21 20:38:37"
  },
  {
    "type": "chat",
    "user": "bari.mart0",
    "content": "a rejoint le live",
    "datetime": "2026-04-21 20:38:37"
  },
  {
    "type": "chat",
    "user": "sylviane.p22",
    "content": "a rejoint le live",
    "datetime": "2026-04-21 20:38:38"
  },
  {
    "type": "like",
    "user": "mr.propre51_",
    "content": "?",
    "datetime": "2026-04-21 20:38:38"
  },
  {
    "type": "chat",
    "user": "robarashid6",
    "content": "a rejoint le live",
    "datetime": "2026-04-21 20:38:39"
  },
  {
    "type": "chat",
    "user": "pereeez17.17",
    "content": "a rejoint le live",
    "datetime": "2026-04-21 20:38:39"
  },
  {
    "type": "like",
    "user": "mr.propre51_",
    "content": "?",
    "datetime": "2026-04-21 20:38:39"
  },
  {
    "type": "like",
    "user": "mr.propre51_",
    "content": "?",
    "datetime": "2026-04-21 20:38:42"
  },
  {
    "type": "chat",
    "user": "antonycaffier13130",
    "content": "a rejoint le live",
    "datetime": "2026-04-21 20:38:43"
  },
  {
    "type": "chat",
    "user": "mo78888888888",
    "content": "a rejoint le live",
    "datetime": "2026-04-21 20:38:46"
  },
  {
    "type": "like",
    "user": "mr.propre51_",
    "content": "?",
    "datetime": "2026-04-21 20:38:47"
  },
  {
    "type": "chat",
    "user": "jhonrangga464",
    "content": "a rejoint le live",
    "datetime": "2026-04-21 20:38:49"
  },
  {
    "type": "chat",
    "user": "alpp_13",
    "content": "a rejoint le live",
    "datetime": "2026-04-21 20:38:50"
  },
  {
    "type": "chat",
    "user": "orlea66",
    "content": "Équipe au top",
    "datetime": "2026-04-21 20:38:50"
  },
  {
    "type": "chat",
    "user": "gitan526",
    "content": "a rejoint le live",
    "datetime": "2026-04-21 20:38:52"
  },
  {
    "type": "like",
    "user": "mr.propre51_",
    "content": "?",
    "datetime": "2026-04-21 20:38:56"
  },
  {
    "type": "like",
    "user": "mr.propre51_",
    "content": "?",
    "datetime": "2026-04-21 20:38:58"
  },
  {
    "type": "like",
    "user": "viraltiktok8389",
    "content": "?",
    "datetime": "2026-04-21 20:38:59"
  },
  {
    "type": "chat",
    "user": "belcy7921",
    "content": "a rejoint le live",
    "datetime": "2026-04-21 20:39:01"
  }
]